pyscreeps_arena/__init__.py
pyscreeps_arena/build.py
pyscreeps_arena/compiler.py
pyscreeps_arena/localization.py
pyscreeps_arena/project.7z
pyscreeps_arena/core/__init__.py
pyscreeps_arena/core/basic.py
pyscreeps_arena/core/config.py
pyscreeps_arena/core/const.py
pyscreeps_arena/core/core.py
pyscreeps_arena/core/main.py
pyscreeps_arena/core/utils.py
pyscreeps_arena/ui/P2PY.py
pyscreeps_arena/ui/__init__.py
pyscreeps_arena/ui/creeplogic_edit.py
pyscreeps_arena/ui/map_render.py
pyscreeps_arena/ui/mapviewer.py
pyscreeps_arena/ui/project_ui.py
pyscreeps_arena/ui/rs_icon.py
pyscreeps_arena/ui/qcreeplogic/__init__.py
pyscreeps_arena/ui/qcreeplogic/model.py
pyscreeps_arena/ui/qcreeplogic/qcreeplogic.py
pyscreeps_arena/ui/qmapker/__init__.py
pyscreeps_arena/ui/qmapker/qmapmarker.py
pyscreeps_arena/ui/qmapker/qvariable.py
pyscreeps_arena/ui/qmapker/test_compact_variable.py
pyscreeps_arena/ui/qmapker/test_qmapmarker.py
pyscreeps_arena/ui/qmapker/test_qvariable.py
pyscreeps_arena/ui/qmapker/to_code.py
pyscreeps_arena/ui/qmapv/__init__.py
pyscreeps_arena/ui/qmapv/qcinfo.py
pyscreeps_arena/ui/qmapv/qco.py
pyscreeps_arena/ui/qmapv/qmapv.py
pyscreeps_arena/ui/qmapv/test_array_drag.py
pyscreeps_arena/ui/qmapv/test_drag.py
pyscreeps_arena/ui/qmapv/test_qcinfo.py
pyscreeps_arena/ui/qmapv/test_qco_drag.py
pyscreeps_arena/ui/qmapv/test_qmapv.py
pyscreeps_arena/ui/qmapv/test_simple_array.py
pyscreeps_arena/ui/qrecipe/__init__.py
pyscreeps_arena/ui/qrecipe/model.py
pyscreeps_arena/ui/qrecipe/qrecipe.py
pyscreeps_arena-0.5.8.1.dist-info/METADATA
pyscreeps_arena-0.5.8.1.dist-info/WHEEL
pyscreeps_arena-0.5.8.1.dist-info/entry_points.txt
pyscreeps_arena-0.5.8.1.dist-info/top_level.txt
pyscreeps_arena-0.5.8.1.dist-info/RECORD
