Metadata-Version: 2.4
Name: pyscreeps-arena
Version: 0.5.8.1
Summary: Python api|interface to play game: Screeps: Arena.
Author-email: 2229066748@qq.com
Maintainer: Eagle'sBaby
Maintainer-email: 2229066748@qq.com
License: Apache Licence 2.0
Keywords: python,screeps:arena,screeps
Classifier: Programming Language :: Python
Classifier: Programming Language :: Python :: 3
Requires-Python: >=3.10
Requires-Dist: pyperclip
Requires-Dist: colorama
Requires-Dist: py7zr
Requires-Dist: chardet
Requires-Dist: Transcrypt==3.9.1
Requires-Dist: PyQt6
Requires-Dist: mkdocs
Requires-Dist: mkdocstrings[python]
Requires-Dist: mkdocs-material
Dynamic: author-email
Dynamic: classifier
Dynamic: description
Dynamic: description-content-type
Dynamic: keywords
Dynamic: license
Dynamic: maintainer
Dynamic: maintainer-email
Dynamic: requires-dist
Dynamic: requires-python
Dynamic: summary
